spins2/__init__.py
spins2/functions.py
spins2/plots.py
spins2/wrapper.py
spins2/ising/__init__.py
spins2/ising/bilayer_aa.py
spins2/ising/bilayer_aa_update.py
spins2/ising/bilayer_ab.py
spins2/ising/bilayer_ab_update.py
spins2/ising/square.py
spins2/ising/square_update.py
spins2/ising/triangular.py
spins2/ising/triangular_update.py
spins2/single/__init__.py
spins2/single/bilayer_aa.py
spins2/single/bilayer_aa_update.py
spins2/single/bilayer_ab.py
spins2/single/bilayer_ab_update.py
spins2/single/square.py
spins2/single/square_update.py
spins2/single/triangular.py
spins2/single/triangular_update.py
spins2-0.0.3.4.dist-info/METADATA
spins2-0.0.3.4.dist-info/WHEEL
spins2-0.0.3.4.dist-info/entry_points.txt
spins2-0.0.3.4.dist-info/top_level.txt
spins2-0.0.3.4.dist-info/RECORD
