Metadata-Version: 2.1
Name: spins2
Version: 0.0.3.4
Summary: A Monte Carlo Simulation Code for the Phase Transition in 2D/3D Magnetic Materials.
Home-page: https://github.com/lkccrr/spins2
Author: kan
Author-email: luokan@mail.ecust.edu.cn
License: MIT
Keywords: Monte Carlo Simulation Ising Model
Platform: Unix
Platform: Windows
Classifier: License :: OSI Approved :: MIT License
Classifier: Programming Language :: Python
Classifier: Programming Language :: Python :: 3
Classifier: Programming Language :: Python :: 3 :: Only
Classifier: Programming Language :: Python :: 3.8
Classifier: Programming Language :: Python :: 3.9
Classifier: Programming Language :: Python :: 3.10
Classifier: Programming Language :: Python :: 3.11
Classifier: Programming Language :: Python :: 3.12
Requires-Python: >=3.8
Requires-Dist: numba >=0.54.0
Requires-Dist: numpy >=1.22.0
Requires-Dist: matplotlib >=3.6.0
